{
  "attributes": [
    {
      "allow_nil?": false,
      "default": "fragment(\"uuid_generate_v7()\")",
      "generated?": false,
      "primary_key?": true,
      "references": null,
      "size": null,
      "source": "id",
      "type": "uuid"
    },
    {
      "allow_nil?": false,
      "default": "nil",
      "generated?": false,
      "primary_key?": false,
      "references": null,
      "size": null,
      "source": "name",
      "type": "text"
    },
    {
      "allow_nil?": false,
      "default": "nil",
      "generated?": false,
      "primary_key?": false,
      "references": null,
      "size": null,
      "source": "description",
      "type": "text"
    },
    {
      "allow_nil?": false,
      "default": "fragment(\"(now() AT TIME ZONE 'utc')\")",
      "generated?": false,
      "primary_key?": false,
      "references": null,
      "size": null,
      "source": "inserted_at",
      "type": "utc_datetime_usec"
    },
    {
      "allow_nil?": false,
      "default": "fragment(\"(now() AT TIME ZONE 'utc')\")",
      "generated?": false,
      "primary_key?": false,
      "references": null,
      "size": null,
      "source": "updated_at",
      "type": "utc_datetime_usec"
    }
  ],
  "base_filter": null,
  "check_constraints": [],
  "custom_indexes": [],
  "custom_statements": [],
  "has_create_action": true,
  "hash": "0932C70C8C22FCA2F0C712B8360DBD2B8D8300ADFA956A361AEA09420C2DEA85",
  "identities": [],
  "multitenancy": {
    "attribute": null,
    "global": false,
    "strategy": "context"
  },
  "repo": "Elixir.Zippiker.Repo",
  "schema": null,
  "table": "groups"
}